easy_pika/__init__.py
easy_pika/pika_obj.py
easy_pika/test.py
easypikaio-0.0.3.dist-info/METADATA
easypikaio-0.0.3.dist-info/WHEEL
easypikaio-0.0.3.dist-info/top_level.txt
easypikaio-0.0.3.dist-info/RECORD
