Metadata-Version: 2.1
Name: easypikaio
Version: 0.0.3
Summary: Library for easy connection to rabbitmq  with pika Library
Author: mohsen akbari (malevin)
Author-email: malevin.git@gmail.com
License: UNKNOWN
Keywords: python,pika,amqp,rabbitmq,iot,easy
Platform: UNKNOWN
Classifier: Development Status :: 1 - Planning
Classifier: Intended Audience :: Developers
Classifier: Programming Language :: Python :: 3
Classifier: Operating System :: Unix
Classifier: Operating System :: MacOS :: MacOS X
Classifier: Operating System :: Microsoft :: Windows
Requires-Dist: pika
